quantuloop_aws_client/__init__.py
quantuloop_aws_client/libquloop_simulation_client.so
quantuloop_aws_client-2024.2.dist-info/LICENSE
quantuloop_aws_client-2024.2.dist-info/METADATA
quantuloop_aws_client-2024.2.dist-info/WHEEL
quantuloop_aws_client-2024.2.dist-info/RECORD
quantuloop_aws_client.libs/libcrypto-ce0fec9c.so.1.1
quantuloop_aws_client.libs/libssl-aaaf241b.so.1.1
